setup.py
TRNLTK.egg-info/PKG-INFO
TRNLTK.egg-info/SOURCES.txt
TRNLTK.egg-info/dependency_links.txt
TRNLTK.egg-info/top_level.txt
trnltk/__init__.py
trnltk/experiments/__init__.py
trnltk/experiments/dictionaryexperiments.py
trnltk/experiments/parsesetexperiments.py
trnltk/morphology/__init__.py
trnltk/morphology/contextful/__init__.py
trnltk/morphology/contextful/likelihoodmetrics/__init__.py
trnltk/morphology/contextful/likelihoodmetrics/contextlessdistribution/__init__.py
trnltk/morphology/contextful/likelihoodmetrics/contextlessdistribution/contextlessdistributioncalculator.py
trnltk/morphology/contextful/likelihoodmetrics/contextlessdistribution/contextlessdistributionsmoother.py
trnltk/morphology/contextful/likelihoodmetrics/contextlessdistribution/test/__init__.py
trnltk/morphology/contextful/likelihoodmetrics/contextlessdistribution/test/test_contextlessdistributioncalculator.py
trnltk/morphology/contextful/likelihoodmetrics/contextlessdistribution/test/test_simplegoodturingcontextlessdistributionsmoother.py
trnltk/morphology/contextful/likelihoodmetrics/hidden/__init__.py
trnltk/morphology/contextful/likelihoodmetrics/hidden/database.py
trnltk/morphology/contextful/likelihoodmetrics/hidden/ngramtypefrequencyfinder.py
trnltk/morphology/contextful/likelihoodmetrics/hidden/query.py
trnltk/morphology/contextful/likelihoodmetrics/hidden/querykeyappender.py
trnltk/morphology/contextful/likelihoodmetrics/hidden/simplegoodturing.py
trnltk/morphology/contextful/likelihoodmetrics/hidden/targetformgivencontextcounter.py
trnltk/morphology/contextful/likelihoodmetrics/hidden/test/__init__.py
trnltk/morphology/contextful/likelihoodmetrics/hidden/test/test_simplegoodturing.py
trnltk/morphology/contextful/likelihoodmetrics/wordformcollocation/__init__.py
trnltk/morphology/contextful/likelihoodmetrics/wordformcollocation/contextparsingcalculator.py
trnltk/morphology/contextful/likelihoodmetrics/wordformcollocation/interpolatingcalculator.py
trnltk/morphology/contextful/likelihoodmetrics/wordformcollocation/ngramfrequencysmoother.py
