Metadata-Version: 1.2
Name: TRNLTK
Version: 0.0.1
Summary: Turkish Natural Language Toolkit
Home-page: https://github.com/aliok/trnltk
Author: Ali Ok
Author-email: aliok@apache.org
Maintainer: Ali Ok
Maintainer-email: aliok@apache.org
License: Apache 2
Platform: UNKNOWN
Classifier: License :: OSI Approved :: Python Software Foundation License
